AUTHORS.rst
Changelog.rst
FuturePlans.rst
INSTALL.rst
LICENSE.rst
MANIFEST.in
README.rst
compiler_opt.py
pct-speedtest.py
setup.cfg
setup.py
.github/workflows/codeql-analysis.yml
.github/workflows/integration.yml
.github/workflows/wheels.yml
Doc/Changelog.pycrypto
Doc/Makefile
Doc/conf.py
Doc/index.rst
Doc/make.bat
Doc/python-3-changes.txt
Doc/LEGAL/00INDEX
Doc/LEGAL/COPYRIGHT.pycrypto
Doc/LEGAL/tsu-notify.mbox
Doc/LEGAL/copy/00INDEX
Doc/LEGAL/copy/LICENSE.libtom
Doc/LEGAL/copy/LICENSE.orig
Doc/LEGAL/copy/LICENSE.python-2.2
Doc/LEGAL/copy/stmts/Andrew_M_Kuchling.mbox
Doc/LEGAL/copy/stmts/Barry_A_Warsaw.mbox
Doc/LEGAL/copy/stmts/Jeethu_Rao.mbox
Doc/LEGAL/copy/stmts/Joris_Bontje.mbox
Doc/LEGAL/copy/stmts/Mark_Moraes.mbox
Doc/LEGAL/copy/stmts/Paul_Swartz.mbox
Doc/LEGAL/copy/stmts/Robey_Pointer.asc
Doc/LEGAL/copy/stmts/Wim_Lewis.asc
Doc/_static/theme_overrides.css
Doc/ocb/README.txt
Doc/ocb/license1.pdf
Doc/ocb/license2.pdf
Doc/ocb/license3.pdf
Doc/sphinx_rtd_theme/__init__.py
Doc/sphinx_rtd_theme/breadcrumbs.html
Doc/sphinx_rtd_theme/footer.html
Doc/sphinx_rtd_theme/layout.html
Doc/sphinx_rtd_theme/search.html
Doc/sphinx_rtd_theme/searchbox.html
Doc/sphinx_rtd_theme/theme.conf
Doc/sphinx_rtd_theme/versions.html
Doc/sphinx_rtd_theme/static/css/badge_only.css
Doc/sphinx_rtd_theme/static/css/badge_only.css.map
Doc/sphinx_rtd_theme/static/css/theme.css
Doc/sphinx_rtd_theme/static/css/theme.css.map
Doc/sphinx_rtd_theme/static/fonts/FontAwesome.otf
Doc/sphinx_rtd_theme/static/fonts/Inconsolata-Bold.ttf
Doc/sphinx_rtd_theme/static/fonts/Inconsolata-Regular.ttf
Doc/sphinx_rtd_theme/static/fonts/Lato-Bold.ttf
Doc/sphinx_rtd_theme/static/fonts/Lato-Regular.ttf
Doc/sphinx_rtd_theme/static/fonts/RobotoSlab-Bold.ttf
Doc/sphinx_rtd_theme/static/fonts/RobotoSlab-Regular.ttf
Doc/sphinx_rtd_theme/static/fonts/fontawesome-webfont.eot
Doc/sphinx_rtd_theme/static/fonts/fontawesome-webfont.svg
Doc/sphinx_rtd_theme/static/fonts/fontawesome-webfont.ttf
lib/pycryptocore.egg-info/PKG-INFO
lib/pycryptocore.egg-info/SOURCES.txt
lib/pycryptocore.egg-info/dependency_links.txt
lib/pycryptocore.egg-info/not-zip-safe
lib/pycryptocore.egg-info/requires.txt
lib/pycryptocore.egg-info/top_level.txt
