Metadata-Version: 1.2
Name: pycryptocore
Version: 0.0.3
Summary: CryptoCoregraphic library for Python
Home-page: https://www.pycryptocore.org
Author: Helder Eijs
Author-email: helderijs@gmail.com
License: BSD, Public Domain
Project-URL: Source, https://github.com/Legrandin/pycryptocore/
Platform: Posix; MacOS X; Windows
Classifier: Development Status :: 5 - Production/Stable
Classifier: License :: OSI Approved :: BSD License
Classifier: License :: OSI Approved :: Apache Software License
Classifier: License :: Public Domain
Classifier: Intended Audience :: Developers
Classifier: Operating System :: Unix
Classifier: Operating System :: Microsoft :: Windows
Classifier: Operating System :: MacOS :: MacOS X
Classifier: Topic :: Security :: Cryptography
Classifier: Programming Language :: Python :: 2
Classifier: Programming Language :: Python :: 2.7
Classifier: Programming Language :: Python :: 3
Classifier: Programming Language :: Python :: 3.5
Classifier: Programming Language :: Python :: 3.6
Classifier: Programming Language :: Python :: 3.7
Classifier: Programming Language :: Python :: 3.8
Classifier: Programming Language :: Python :: 3.9
Requires-Python: >=2.7, !=3.0.*, !=3.1.*, !=3.2.*, !=3.3.*, !=3.4.*
